sylib/__init__.py
sylib/converters.py
sylib/datasource_conversion.py
sylib/error.py
sylib/filenames.py
sylib/fx_selector.py
sylib/index.py
sylib/json_table.py
sylib/librarytag_sylib.py
sylib/lookup.py
sylib/lookup_gui.py
sylib/mdflib.py
sylib/odbc.py
sylib/sort.py
sylib/table_importer_gui.py
sylib/table_sources.py
sylib/url.py
sylib/util.py
sylib/vjoin.py
sylib/widget_library.py
sylib/xl_utils.py
sylib/bokeh/backend.py
sylib/bokeh/bokeh.py
sylib/bokeh/bokeh.svg
sylib/bokeh/bokeh_viewer.py
sylib/bokeh/drawing.py
sylib/bokeh/exporter.py
sylib/calculator/calculator_gui.py
sylib/calculator/calculator_model.py
sylib/calculator/plugins.py
sylib/calculator/std_plugin/basics.py
sylib/calculator/std_plugin/event_detection.py
sylib/calculator/std_plugin/logics.py
sylib/calculator/std_plugin/plugin_std.py
sylib/examples/Analysis/Signal Processing/DetrendADAF.syx
sylib/examples/Analysis/Signal Processing/FilterADAFs.syx
sylib/examples/Analysis/Signal Processing/InterpolateADAFs.syx
sylib/examples/Analysis/Signal Processing/SequenceSplit.syx
sylib/examples/Analysis/Statistic/HeatmapCalculation.syx
sylib/examples/Analysis/Statistic/HistogramCalculation.syx
sylib/examples/Data Processing/Calculate/Calculator.syx
sylib/examples/Data Processing/Calculate/CalculatorAdvanced.syx
sylib/examples/Data Processing/Calculate/Functions.syx
sylib/examples/Data Processing/Calculate/MatlabTable.syx
sylib/examples/Data Processing/Calculate/Example files/function_example_scripts.py
sylib/examples/Data Processing/Calculate/Example files/matlab_example_script.m
sylib/examples/Data Processing/Convert/ADAF2Table.syx
sylib/examples/Data Processing/Convert/Datasource2Table.syx
sylib/examples/Data Processing/Convert/JSON.syx
sylib/examples/Data Processing/Convert/Table2ADAF.syx
sylib/examples/Data Processing/Convert/Table2Datasources.syx
sylib/examples/Data Processing/Convert/Table2Text.syx
sylib/examples/Data Processing/Convert/Text2Table.syx
Sympathy-4.0.1.dist-info/LICENSE.txt
Sympathy-4.0.1.dist-info/METADATA
Sympathy-4.0.1.dist-info/WHEEL
Sympathy-4.0.1.dist-info/entry_points.txt
Sympathy-4.0.1.dist-info/top_level.txt
Sympathy-4.0.1.dist-info/RECORD
